{
  "users": [
    {
      "id": 0,
      "username": "3028",
      "token": "c43140d34c5da504c30d"
    },
    {
      "id": 1,
      "username": "8803",
      "token": "516d6316aa43aa01b552"
    },
    {
      "id": 2,
      "username": "3773",
      "token": "b433b024163b000a524d"
    },
    {
      "id": 3,
      "username": "8244",
      "token": "62c3cda20c225a056555"
    },
    {
      "id": 4,
      "username": "7885",
      "token": "01b54ac5a0364213c1b6"
    },
    {
      "id": 5,
      "username": "7006",
      "token": "3a16d3423d360cc50343"
    },
    {
      "id": 6,
      "username": "3294",
      "token": "b3c146bb2db644aa3c61"
    },
    {
      "id": 7,
      "username": "9258",
      "token": "d063a505a1b15526d35a"
    },
    {
      "id": 8,
      "username": "2765",
      "token": "6d5533b1d206362c3154"
    },
    {
      "id": 9,
      "username": "2849",
      "token": "6163a33b2260d30d0caa"
    }
  ],
  "tasks": [
    {
      "id": 0,
      "userId": 0,
      "title": "harum",
      "description": "Laborum voluptas ab est quaerat."
    },
    {
      "id": 1,
      "userId": 1,
      "title": "numquam",
      "description": "Hic assumenda magni maiores fuga omnis doloribus et qui. Sapiente aliquam debitis eius accusantium nihil voluptates quam quia officiis."
    },
    {
      "id": 2,
      "userId": 2,
      "title": "harum",
      "description": "Hic harum quasi perspiciatis error delectus corrupti at soluta. Iure quaerat laudantium ipsum harum minus eum. Rem vitae sit maiores doloremque quos."
    },
    {
      "id": 3,
      "userId": 3,
      "title": "maxime",
      "description": "Ea voluptas commodi aliquid facilis consectetur excepturi maiores cumque facilis. Dolore facere iste quisquam sit. Consectetur nisi qui architecto minima sint adipisci exercitationem sint. Modi reiciendis cupiditate repellendus doloribus."
    },
    {
      "id": 4,
      "userId": 4,
      "title": "facilis",
      "description": "Placeat unde esse. Sapiente architecto soluta deserunt neque. Fuga sit deserunt debitis laboriosam quia quis rerum quam."
    },
    {
      "id": 5,
      "userId": 5,
      "title": "neque",
      "description": "Repudiandae impedit enim cumque. Facere aperiam illo earum incidunt voluptas eveniet libero."
    },
    {
      "id": 6,
      "userId": 6,
      "title": "dolorum",
      "description": "Illum nisi fugit nam omnis."
    },
    {
      "id": 7,
      "userId": 7,
      "title": "officia",
      "description": "Tenetur quod culpa accusamus laboriosam. Veritatis deleniti adipisci suscipit ut commodi dolore. Deleniti et dicta consectetur nihil voluptates. Fugiat atque hic eum possimus praesentium commodi."
    },
    {
      "id": 8,
      "userId": 8,
      "title": "iusto",
      "description": "Unde illum nam. Voluptatum molestiae iure temporibus dolorem odit dignissimos sunt sed ratione."
    },
    {
      "id": 9,
      "userId": 9,
      "title": "omnis",
      "description": "Pariatur fugiat accusantium maiores. Molestiae error nisi consequuntur tempora alias consequatur vel inventore."
    }
  ]
}